cwikibot/__init__.py
cwikibot/__main__.py
cwikibot/gui_test.py
cwikibot/wiki.py
cwikibot/core/__init__.py
cwikibot/core/api.py
cwikibot/core/category.py
cwikibot/core/color_cmdline.py
cwikibot/core/date.py
cwikibot/core/diff.py
cwikibot/core/page.py
cwikibot/core/query.py
cwikibot/core/search.py
cwikibot/core/user.py
cwikibot-0.0.4.dist-info/LICENSE.md
cwikibot-0.0.4.dist-info/METADATA
cwikibot-0.0.4.dist-info/WHEEL
cwikibot-0.0.4.dist-info/top_level.txt
cwikibot-0.0.4.dist-info/RECORD
