Metadata-Version: 2.1
Name: cwikibot
Version: 0.0.4
Summary: simple mediawiki bot
Home-page: https://gitlab.com/caeruleum/cwikibot
Author: caeruleum
Author-email: ceruleanxyz@gmail.com
License: MIT
Project-URL: Documentation, https://gitlab.com/caeruleum/cwikibot
Project-URL: Source, https://gitlab.com/caeruleum/cwikibot
Platform: any
Classifier: Topic :: Utilities
Classifier: Topic :: Internet :: WWW/HTTP :: Dynamic Content :: Wiki
Classifier: Programming Language :: Python
Classifier: Programming Language :: Python :: 3.8
Classifier: Programming Language :: Python :: 3.9
Classifier: Programming Language :: Python :: 3.10
Classifier: Programming Language :: Python :: 3 :: Only
Classifier: Intended Audience :: Developers
Classifier: License :: OSI Approved :: MIT License
Classifier: Operating System :: OS Independent
Requires-Python: >=3.8
License-File: LICENSE.md
Requires-Dist: requests
Requires-Dist: typing-extensions
Requires-Dist: python-dateutil
